pyramid_dogpile_cache2/__init__.py
pyramid_dogpile_cache2/cache.py
pyramid_dogpile_cache2/pylibmc.py
pyramid_dogpile_cache2/tests/__init__.py
pyramid_dogpile_cache2/tests/conftest.py
pyramid_dogpile_cache2/tests/test_cache.py
pyramid_dogpile_cache2/tests/test_configuration.py
pyramid_dogpile_cache2-1.2.0.dist-info/METADATA
pyramid_dogpile_cache2-1.2.0.dist-info/WHEEL
pyramid_dogpile_cache2-1.2.0.dist-info/licenses/LICENSE
pyramid_dogpile_cache2-1.2.0.dist-info/RECORD
