Metadata-Version: 2.4
Name: pyramid_dogpile_cache2
Version: 1.2.0
Summary: Integrates dogpile.cache for Pyramid
Project-URL: repository, https://github.com/zeitonline/pyramid_dogpile_cache2
Author-email: DIE ZEIT <engineering@zeit.de>
License: BSD-3-Clause
License-File: LICENSE
Keywords: dogpile.cache,pyramid
Classifier: Environment :: Plugins
Classifier: Framework :: Pyramid
Classifier: Intended Audience :: Developers
Classifier: License :: OSI Approved :: BSD License
Requires-Python: >=3.7
Requires-Dist: dogpile-cache>=1.0.0.dev0
Requires-Dist: pyramid-dogpile-cache
